sendgrify/__init__.py
sendgrify/core.py
sendgrify-2.0.3.dist-info/LICENSE
sendgrify-2.0.3.dist-info/METADATA
sendgrify-2.0.3.dist-info/WHEEL
sendgrify-2.0.3.dist-info/top_level.txt
sendgrify-2.0.3.dist-info/RECORD
