Metadata-Version: 2.1
Name: sendgrify
Version: 2.0.3
Summary: SendGrid for Humans
Home-page: https://github.com/sdelquin/sendgrify.git
Author: Sergio Delgado Quintero
Author-email: sdelquin@gmail.com
License: MIT
License-File: LICENSE
Requires-Dist: sendgrid (==5.3.0)
Requires-Dist: markdown
